metaphor/__main__.py
metaphor/alation/README.md
metaphor/alation/__init__.py
metaphor/alation/client.py
metaphor/alation/config.py
metaphor/alation/extractor.py
metaphor/alation/schema.py
metaphor/athena/README.md
metaphor/athena/__init__.py
metaphor/athena/config.py
metaphor/athena/extractor.py
metaphor/athena/models.py
metaphor/azure_data_factory/__init__.py
metaphor/azure_data_factory/config.py
metaphor/azure_data_factory/extractor.py
metaphor/azure_data_factory/readme.md
metaphor/azure_data_factory/utils.py
metaphor/bigquery/README.md
metaphor/bigquery/__init__.py
metaphor/bigquery/config.py
metaphor/bigquery/extractor.py
metaphor/bigquery/job_change_event.py
metaphor/bigquery/lineage/README.md
metaphor/bigquery/lineage/__init__.py
metaphor/bigquery/lineage/config.py
metaphor/bigquery/lineage/extractor.py
metaphor/bigquery/log_filter.py
metaphor/bigquery/log_type.py
metaphor/bigquery/profile/README.md
metaphor/bigquery/profile/__init__.py
metaphor/bigquery/profile/config.py
metaphor/bigquery/profile/extractor.py
metaphor/bigquery/queries.py
metaphor/bigquery/schema_field.py
metaphor/bigquery/table.py
metaphor/bigquery/utils.py
metaphor/common/__init__.py
metaphor/common/api_request.py
metaphor/common/aws.py
metaphor/common/base_config.py
metaphor/common/base_extractor.py
metaphor/common/cli.py
metaphor/common/column_statistics.py
metaphor/common/constants.py
metaphor/common/dataclass.py
metaphor/common/docs/column_statistics.md
metaphor/common/docs/env_var.md
metaphor/common/docs/filter.md
metaphor/common/docs/git_repo.md
metaphor/common/docs/output.md
metaphor/common/docs/process_query.md
metaphor/common/docs/requests.md
metaphor/common/docs/sampling.md
metaphor/common/docs/tag_matcher.md
metaphor/common/embeddings.py
metaphor/common/embeddings_config.py
metaphor/common/entity_id.py
metaphor/common/event_util.py
metaphor/common/fieldpath.py
metaphor/common/file_sink.py
metaphor/common/filter.py
metaphor/common/git.py
metaphor/common/hierarchy.py
metaphor_connectors-0.14.182.dist-info/LICENSE
metaphor_connectors-0.14.182.dist-info/METADATA
metaphor_connectors-0.14.182.dist-info/WHEEL
metaphor_connectors-0.14.182.dist-info/entry_points.txt
metaphor_connectors-0.14.182.dist-info/RECORD
