Metadata-Version: 2.1
Name: metaphor-connectors
Version: 0.14.182
Summary: A collection of Python-based 'connectors' that extract metadata from various sources to ingest into the Metaphor app.
Home-page: https://metaphor.io
License: Apache-2.0
Author: Metaphor
Author-email: dev@metaphor.io
Requires-Python: >=3.9,<3.12
Classifier: License :: OSI Approved :: Apache Software License
Classifier: Programming Language :: Python :: 3
Classifier: Programming Language :: Python :: 3.9
Classifier: Programming Language :: Python :: 3.10
Classifier: Programming Language :: Python :: 3.11
Provides-Extra: all
Provides-Extra: bigquery
Provides-Extra: confluence
Provides-Extra: datafactory
Provides-Extra: datahub
Provides-Extra: dbt
Provides-Extra: great-expectations
Provides-Extra: hive
Provides-Extra: kafka
Provides-Extra: looker
Provides-Extra: metabase
Provides-Extra: monday
Provides-Extra: mongodb
Provides-Extra: monte-carlo
Provides-Extra: mssql
Provides-Extra: mysql
Provides-Extra: notion
Provides-Extra: oracle
Provides-Extra: postgresql
Provides-Extra: power-bi
Provides-Extra: quicksight
Provides-Extra: redshift
Provides-Extra: s3
Provides-Extra: sharepoint
Provides-Extra: snowflake
Provides-Extra: static-web
Provides-Extra: synapse
Provides-Extra: tableau
Provides-Extra: thought-spot
Provides-Extra: trino
Provides-Extra: unity-catalog
Requires-Dist: GitPython (>=3.1.37,<4.0.0) ; extra == "all" or extra == "looker"
Requires-Dist: PyYAML (>=6.0,<7.0)
Requires-Dist: SQLAlchemy (>=2.0.31,<3.0.0) ; extra == "all" or extra == "great-expectations" or extra == "mysql" or extra == "oracle"
Requires-Dist: asyncpg (>=0.30.0,<0.31.0) ; extra == "all" or extra == "postgresql" or extra == "redshift"
Requires-Dist: avro (>=1.11.3,<2.0.0) ; extra == "all" or extra == "kafka"
Requires-Dist: aws-assume-role-lib (>=2.10.0,<3.0.0)
Requires-Dist: azure-identity (>=1.19.0,<2.0.0) ; extra == "all" or extra == "datafactory" or extra == "sharepoint"
Requires-Dist: azure-mgmt-datafactory (>=9.0.0,<10.0.0) ; extra == "all" or extra == "datafactory"
Requires-Dist: beautifulsoup4 (>=4.12.3,<5.0.0) ; extra == "all" or extra == "sharepoint" or extra == "static-web"
Requires-Dist: boto3 (>=1.35.19,<2.0.0) ; extra == "quicksight"
Requires-Dist: botocore (>=1.35.19,<2.0.0) ; extra == "quicksight"
Requires-Dist: canonicaljson (>=2.0.0,<3.0.0)
Requires-Dist: confluent-kafka (>=2.7.0,<3.0.0) ; extra == "all" or extra == "kafka"
Requires-Dist: databricks-sdk (>=0.40.0,<0.41.0) ; extra == "all" or extra == "unity-catalog"
Requires-Dist: databricks-sql-connector (>=3.7.0,<4.0.0) ; extra == "all" or extra == "unity-catalog"
Requires-Dist: fastavro (>=1.9.2,<2.0.0) ; extra == "all" or extra == "s3"
Requires-Dist: func-timeout (>=4.3.5,<5.0.0) ; extra == "all" or extra == "quicksight"
Requires-Dist: google-cloud-bigquery (>=3.25.0,<4.0.0) ; extra == "all" or extra == "bigquery"
Requires-Dist: google-cloud-logging (>=3.5.0,<4.0.0) ; extra == "all" or extra == "bigquery"
Requires-Dist: gql[requests] (>=3.5.0,<4.0.0) ; extra == "all" or extra == "datahub"
Requires-Dist: great-expectations (>=1.2.0,<2.0.0) ; extra == "all" or extra == "great-expectations"
Requires-Dist: grpcio-tools (>=1.59.3,<2.0.0) ; extra == "all" or extra == "kafka"
Requires-Dist: httpx (>=0.28.1,<0.29.0) ; extra == "all" or extra == "dbt"
Requires-Dist: jsonschema (>=4.23.0,<5.0.0)
Requires-Dist: lkml (>=1.3.6,<2.0.0) ; extra == "all" or extra == "looker"
Requires-Dist: llama-index (>=0.10.19,<0.11.0) ; extra == "all" or extra == "confluence" or extra == "monday" or extra == "notion" or extra == "sharepoint" or extra == "static-web"
Requires-Dist: llama-index-embeddings-azure-openai (>=0.1.6,<0.2.0) ; extra == "all" or extra == "confluence" or extra == "monday" or extra == "notion" or extra == "static-web"
Requires-Dist: llama-index-readers-confluence (>=0.1.4,<0.2.0) ; extra == "all" or extra == "confluence"
Requires-Dist: llama-index-readers-notion (>=0.1.6,<0.2.0) ; extra == "all" or extra == "notion"
Requires-Dist: looker-sdk (>=24.2.0,<25.0.0) ; extra == "all" or extra == "looker"
Requires-Dist: lxml (>=5.0.0,<5.1.0) ; extra == "all" or extra == "sharepoint" or extra == "static-web"
Requires-Dist: metaphor-models (==0.41.3)
Requires-Dist: more-itertools (>=10.1.0,<11.0.0) ; extra == "all" or extra == "s3"
Requires-Dist: msal (>=1.28.0,<2.0.0) ; extra == "all" or extra == "power-bi"
Requires-Dist: msgraph-beta-sdk (>=1.15.0,<1.16.0) ; extra == "all" or extra == "power-bi" or extra == "sharepoint"
Requires-Dist: nltk (>=3.9.1,<4.0.0) ; extra == "all" or extra == "confluence" or extra == "monday" or extra == "notion" or extra == "sharepoint" or extra == "static-web"
Requires-Dist: oracledb (>=2.5.0,<3.0.0) ; extra == "all" or extra == "oracle"
Requires-Dist: parse (>=1.20.0,<2.0.0) ; extra == "all" or extra == "s3"
Requires-Dist: pathvalidate (>=3.2.0,<4.0.0)
Requires-Dist: psycopg2 (>=2.9.10,<3.0.0) ; extra == "all" or extra == "great-expectations"
Requires-Dist: pyarrow[pandas] (>=16.1.0,<17.0.0)
Requires-Dist: pycarlo (>=0.9.0,<0.10.0) ; extra == "all" or extra == "monte-carlo"
Requires-Dist: pydantic[email] (==2.6.4)
Requires-Dist: pyhive (>=0.7.0,<0.8.0) ; extra == "all" or extra == "hive"
Requires-Dist: pymongo (>=4.10.1,<5.0.0) ; extra == "all" or extra == "mongodb"
Requires-Dist: pymssql (>=2.2.11,<2.3.0) ; extra == "all" or extra == "mssql" or extra == "synapse"
Requires-Dist: pymysql (>=1.0.2,<2.0.0) ; extra == "all" or extra == "mysql"
Requires-Dist: python-dateutil (>=2.8.1,<3.0.0)
Requires-Dist: requests (>=2.28.1,<3.0.0)
Requires-Dist: sasl (>=0.3.1,<0.4.0) ; extra == "all" or extra == "hive"
Requires-Dist: smart-open (>=7.0.1,<8.0.0)
Requires-Dist: snowflake-connector-python (>=3.12.3,<4.0.0) ; extra == "all" or extra == "great-expectations" or extra == "snowflake"
Requires-Dist: snowflake-sqlalchemy (>=1.6.1,<2.0.0) ; extra == "all" or extra == "great-expectations"
Requires-Dist: sql-metadata (>=2.10.0,<3.0.0) ; extra == "all" or extra == "bigquery"
Requires-Dist: sqlglot[rs] (>=26.2.0,<27.0.0) ; extra == "all" or extra == "snowflake" or extra == "unity-catalog"
Requires-Dist: sqllineage (>=1.3.8,<1.4.0) ; extra == "all" or extra == "tableau" or extra == "thought-spot"
Requires-Dist: tableauserverclient (>=0.25,<0.26) ; extra == "all" or extra == "tableau"
Requires-Dist: tenacity (>=8.5.0,<9.0.0) ; extra == "all" or extra == "quicksight"
Requires-Dist: thoughtspot_rest_api_v1 (>=1.8.2,<2.0.0) ; extra == "all" or extra == "thought-spot"
Requires-Dist: thrift (>=0.20.0,<0.21.0) ; extra == "all" or extra == "hive"
Requires-Dist: thrift-sasl (>=0.4.3,<0.5.0) ; extra == "all" or extra == "hive"
Requires-Dist: trino (>=0.331.0,<0.332.0) ; extra == "all" or extra == "trino"
Requires-Dist: trio (>=0.28.0,<0.29.0)
Project-URL: Repository, https://github.com/MetaphorData/connectors
